micropype/__init__.py
micropype/__main__.py
micropype/commandline.py
micropype/config.py
micropype/pipelining.py
micropype/utils.py
micropype-0.3.1.dist-info/METADATA
micropype-0.3.1.dist-info/WHEEL
micropype-0.3.1.dist-info/top_level.txt
micropype-0.3.1.dist-info/RECORD
