Metadata-Version: 2.1
Name: micropype
Version: 0.3.1
Summary: Very basic pipelining toolbox
Author: Bastien Cagna
License: BSD 3
Requires-Dist: colorama
Provides-Extra: dev
Requires-Dist: pytest ; extra == 'dev'
